minitap/miniflow/__init__.py
minitap/miniflow/auth.py
minitap/miniflow/cli.py
minitap/miniflow/execution.py
minitap_miniflow-1.0.1.dist-info/WHEEL
minitap_miniflow-1.0.1.dist-info/entry_points.txt
minitap_miniflow-1.0.1.dist-info/METADATA
minitap_miniflow-1.0.1.dist-info/RECORD
