Metadata-Version: 2.3
Name: minitap-miniflow
Version: 1.0.1
Summary: A CLI to run miniflow locally
Author: Clement Guiguet
Requires-Dist: click
Requires-Dist: rich
Requires-Dist: websockets
Requires-Dist: requests
Requires-Dist: keyring
Requires-Dist: ruff>=0.12.10
Requires-Dist: ruff==0.12.10 ; extra == 'dev'
Requires-Python: >=3.12
Project-URL: Homepage, https://minitap.ai/
Project-URL: Source, https://github.com/minitap-ai/miniflow-cli
Provides-Extra: dev
